awair_command_line/__init__.py
awair_command_line/awair.py
awair_command_line/awair_tests.py
awair_command_line/statsd.py
awair_command_line-0.1.5.dist-info/METADATA
awair_command_line-0.1.5.dist-info/WHEEL
awair_command_line-0.1.5.dist-info/entry_points.txt
awair_command_line-0.1.5.dist-info/top_level.txt
awair_command_line-0.1.5.dist-info/RECORD
