Metadata-Version: 2.1
Name: awair-command-line
Version: 0.1.5
Summary: Awair command line. Displays data from all Awair devices on your network. Also shows corresponding Purple Air AQI
Home-page: https://github.com/obradovic/awair-command-line
Author: Zo Obradovic
Author-email: ping@obradovic.com
License: UNKNOWN
Platform: UNKNOWN
Classifier: Programming Language :: Python :: 3
Classifier: License :: OSI Approved :: MIT License
Classifier: Operating System :: OS Independent
Requires-Python: >3.6.0
Requires-Dist: delegator.py (>=0.1.1)
Requires-Dist: datadog (>=0.25.0)
Requires-Dist: python-aqi (>=0.6.1)
Requires-Dist: requests (>=2.0.0)
